fwmp3.py
fwmp3-1.0.1.dist-info/WHEEL
fwmp3-1.0.1.dist-info/METADATA
fwmp3-1.0.1.dist-info/RECORD
