Metadata-Version: 2.1
Name: fwmp3
Version: 1.0.1
Summary: python 3.8
Author: John Smith
Author-email: azarovnick@bk.ru
Requires-Python: >=3.8,<4.0
Classifier: Programming Language :: Python :: 3
Classifier: Programming Language :: Python :: 3.8
Classifier: Programming Language :: Python :: 3.9
